pygamesilent/__init__.py
pygamesilent-1.0.0.dist-info/LICENSE.txt
pygamesilent-1.0.0.dist-info/METADATA
pygamesilent-1.0.0.dist-info/WHEEL
pygamesilent-1.0.0.dist-info/top_level.txt
pygamesilent-1.0.0.dist-info/RECORD
