Metadata-Version: 2.1
Name: pygamesilent
Version: 1.0.0
Summary: Shim around PyGame to hide "Hello" message on import.
Home-page: https://github.com/Julian-O/pygamesilent
Author: Julian-O
Author-email: pygamesilent@somethinkodd.com
License: UNKNOWN
Project-URL: Source, https://github.com/Julian-O/pygamesilent/
Project-URL: PyGame Info, https://pygame.org
Keywords: pygame shim
Platform: UNKNOWN
Classifier: Development Status :: 5 - Production/Stable
Classifier: Programming Language :: Python
Classifier: Intended Audience :: Developers
Classifier: License :: OSI Approved :: MIT License
Classifier: Operating System :: OS Independent
Classifier: Programming Language :: Python :: 2.7
Classifier: Programming Language :: Python :: 3.5
Classifier: Programming Language :: Python :: 3.6
Classifier: Programming Language :: Python :: 3.7
Classifier: Topic :: Software Development :: Libraries :: pygame
Requires-Python: >=2.7, !=3.0.*, !=3.1.*, !=3.2.*, !=3.3.*, !=3.4.*, <4
Requires-Dist: pygame
Provides-Extra: dev
Requires-Dist: check-manifest ; extra == 'dev'
Provides-Extra: test
Requires-Dist: pytest ; extra == 'test'
Requires-Dist: pytest-cov ; extra == 'test'
